Workbook

Sheet Resumo
A1: Relatório de orçamento de hospedagem e domínio
A2: Projeto acadêmico Grupo Êxito Condomínios - comparação feita em 14/10/2026
A5: Meses considerados no orçamento | B5: 12
A6: Domínio .com.br por ano | B6: 40
A8: Comparativo do primeiro ano
A9: Empresa | B9: Plano | C9: Preço/mês | D9: Domínio grátis no 1º ano? | E9: Hospedagem no período | F9: Domínio no período | G9: Total no período | H9: Contrato | I9: Observação
A10: HostGator | B10: Plano P | C10: =HostGator!C6 -> 10.09 | D10: Sim | E10: =C10*$B$5 -> 121.08 | F10: =IF(D10="Sim",0,$B$6*ROUNDUP($B$5/12,0)) -> 0 | G10: =E10+F10 -> 121.08 | H10: 3 anos | I10: 1 site e 1 domínio grátis.
A11: HostGator | B11: Plano M | C11: =HostGator!C7 -> 11.49 | D11: Sim | E11: =C11*$B$5 -> 137.88 | F11: =IF(D11="Sim",0,$B$6*ROUNDUP($B$5/12,0)) -> 0 | G11: =E11+F11 -> 137.88 | H11: 3 anos | I11: Mais de 60 sites e 2 domínios grátis.
A12: HostGator | B12: Plano Turbo | C12: =HostGator!C8 -> 18.69 | D12: Sim | E12: =C12*$B$5 -> 224.28 | F12: =IF(D12="Sim",0,$B$6*ROUNDUP($B$5/12,0)) -> 0 | G12: =E12+F12 -> 224.28 | H12: 3 anos | I12: Para sites com muito acesso; 3 domínios grátis.
A13: Hostinger | B13: Single | C13: =Hostinger!D6 -> 5.99 | D13: Não | E13: =C13*$B$5 -> 71.88 | F13: =IF(D13="Sim",0,$B$6*ROUNDUP($B$5/12,0)) -> 40 | G13: =E13+F13 -> 111.88 | H13: 48 meses | I13: Mais barato por mês, mas sem domínio.
A14: Hostinger | B14: Premium | C14: =Hostinger!D7 -> 10.99 | D14: Sim | E14: =C14*$B$5 -> 131.88 | F14: =IF(D14="Sim",0,$B$6*ROUNDUP($B$5/12,0)) -> 0 | G14: =E14+F14 -> 131.88 | H14: 48 meses | I14: Até 3 sites e domínio grátis por 1 ano.
A15: Hostinger | B15: Unlimited | C15: =Hostinger!D8 -> 13.99 | D15: Sim | E15: =C15*$B$5 -> 167.88 | F15: =IF(D15="Sim",0,$B$6*ROUNDUP($B$5/12,0)) -> 0 | G15: =E15+F15 -> 167.88 | H15: 48 meses | I15: Inclui CDN, IA e suporte prioritário.
A16: Hostinger | B16: Cloud Startup | C16: =Hostinger!D9 -> 39.99 | D16: Sim | E16: =C16*$B$5 -> 479.88 | F16: =IF(D16="Sim",0,$B$6*ROUNDUP($B$5/12,0)) -> 0 | G16: =E16+F16 -> 479.88 | H16: 48 meses | I16: Feito para sites com muito acesso.
A17: Umbler | C17: =Umbler!B5 -> 29 | D17: Não | E17: =C17*$B$5 -> 348 | F17: =IF(D17="Sim",0,$B$6*ROUNDUP($B$5/12,0)) -> 40 | G17: =E17+F17 -> 388 | H17: Mensal | I17: Servidor em nuvem; muito para um site só de HTML e CSS.
A18: Umbler | C18: =Umbler!B6 -> 39 | D18: Não | E18: =C18*$B$5 -> 468 | F18: =IF(D18="Sim",0,$B$6*ROUNDUP($B$5/12,0)) -> 40 | G18: =E18+F18 -> 508 | H18: Mensal | I18: Plano mais vendido da Umbler.
A19: Umbler | C19: =Umbler!B7 -> 60 | D19: Não | E19: =C19*$B$5 -> 720 | F19: =IF(D19="Sim",0,$B$6*ROUNDUP($B$5/12,0)) -> 40 | G19: =E19+F19 -> 760 | H19: Mensal
A20: Umbler | C20: =Umbler!B8 -> 195 | D20: Não | E20: =C20*$B$5 -> 2340 | F20: =IF(D20="Sim",0,$B$6*ROUNDUP($B$5/12,0)) -> 40 | G20: =E20+F20 -> 2380 | H20: Mensal
A21: Umbler | C21: =Umbler!B9 -> 275 | D21: Não | E21: =C21*$B$5 -> 3300 | F21: =IF(D21="Sim",0,$B$6*ROUNDUP($B$5/12,0)) -> 40 | G21: =E21+F21 -> 3340 | H21: Mensal
A23: Menor custo no período | C23: =MIN(G10:G21) -> 111.88 | D23: =INDEX(A10:A21,MATCH(C23,G10:G21,0))&" - "&INDEX(B10:B21,MATCH(C23,G10:G21,0)) -> Hostinger - Single
A25: Conclusão do grupo
A26: 1. Nosso site é feito só com HTML, CSS e JavaScript, então não precisa de servidor em nuvem nem de banco de dados. Os planos da Umbler são mais do que precisamos.
A27: 2. Hostinger Single é o mais barato por mês, mas não tem domínio grátis. Somando o domínio, fica perto do HostGator Plano P e do Hostinger Premium.
A28: 3. HostGator Plano P e Hostinger Premium já incluem o domínio e custam quase o mesmo. Para um site institucional pequeno, qualquer um dos dois atende.
A29: 4. Atenção: os preços promocionais exigem pagar o contrato inteiro de uma vez (HostGator: 3 anos, a partir de R$ 361,61; Hostinger: 48 meses, a partir de R$ 287,52). Depois, o preço sobe.
A30: 5. Os valores são dos prints de 14/10/2026 e podem mudar. Confirme no site antes de contratar.
A32: Legenda
A33: Texto azul | B33: Valor digitado a partir dos prints
A34: Texto preto | B34: Valor calculado por fórmula
A35: Texto verde | B35: Valor puxado de outra aba

Sheet HostGator
A1: HostGator - Planos de hospedagem (ciclo de 3 anos)
A2: Fonte: print da página da HostGator (docs/hospedagem/hostgator.png), consultado em 14/10/2026.
A3: Meses pagos no ciclo: | B3: 36 | C3: +3 meses grátis no ciclo de 3 anos
A5: Plano | B5: Desconto | C5: Preço/mês | D5: Total 3 anos (print) | E5: Preço sem desconto 3 anos | F5: Economia (print) | G5: Domínios grátis | H5: Sites | I5: Armazenamento | J5: Visitas/mês | K5: Contas de e-mail | L5: Servidores
A6: Plano P | B6: 0.78 | C6: 10.09 | D6: 361.61 | E6: 1652.04 | F6: 1389.42 | G6: 1 | H6: 1 | I6: 100 GB NVMe | J6: Até 80 mil | K6: Ilimitadas por 1 ano | L6: No Brasil
A7: Plano M | B7: 0.79 | C7: 11.49 | D7: 412.17 | E7: 2001.24 | F7: 1688.06 | G7: 2 | H7: +60 | I7: 100 GB NVMe | J7: Até 120 mil | K7: Ilimitadas por 1 ano | L7: No Brasil
A8: Plano Turbo | B8: 0.74 | C8: 18.69 | D8: 670.22 | E8: 2663.64 | F8: 2207.4 | G8: 3 | H8: +150 | I8: 150 GB NVMe | J8: Até 400 mil | K8: Ilimitadas por 1 ano | L8: No Brasil
A10: Todos os valores em azul foram copiados do print. O preço por mês tem asterisco no site.
A11: O total de 3 anos é pago de uma vez. Ele não é exatamente o preço/mês x 36, porque o site arredonda o valor mensal.
A12: A economia mostrada pelo site também não é igual a (preço sem desconto - total). Por isso copiamos o valor do print, sem calcular.

Sheet Hostinger
A1: Hostinger - Planos de hospedagem (contrato de 48 meses)
A2: Fonte: print da página da Hostinger (docs/hospedagem/hostinger.png), consultado em 14/10/2026.
A3: Meses do contrato: | B3: 48
A5: Plano | B5: Desconto | C5: Preço normal/mês | D5: Preço promocional/mês | E5: Total do contrato | F5: Total sem desconto | G5: Economia | H5: Renovação/mês | I5: Sites | J5: Armazenamento | K5: Domínio | L5: Backups | M5: Comércio eletrônico | N5: CDN | O5: Ferramentas de IA | P5: Suporte prioritário 24h
A6: Single | B6: 0.8 | C6: 29.99 | D6: 5.99 | E6: =D6*$B$3 -> 287.52 | F6: =C6*$B$3 -> 1439.52 | G6: =F6-E6 -> 1152 | H6: 23.99 | I6: 1 | J6: 10 GB SSD | K6: Não incluso | L6: Semanais | M6: Sim | N6: Não | O6: Não | P6: Não
A7: Premium | B7: 0.76 | C7: 45.99 | D7: 10.99 | E7: =D7*$B$3 -> 527.52 | F7: =C7*$B$3 -> 2207.52 | G7: =F7-E7 -> 1680 | H7: 38.99 | I7: 3 | J7: 20 GB SSD | K7: Grátis por 1 ano | L7: Semanais | M7: Sim | N7: Não | O7: Não | P7: Não
A8: Unlimited | B8: 0.81 | C8: 72.99 | D8: 13.99 | E8: =D8*$B$3 -> 671.52 | F8: =C8*$B$3 -> 3503.52 | G8: =F8-E8 -> 2832 | H8: 64.99 | I8: Ilimitado | J8: 50 GB NVMe | K8: Grátis por 1 ano | L8: Diários | M8: Sim | N8: Sim | O8: Sim | P8: Sim
A9: Cloud Startup | B9: 0.71 | C9: 139.99 | D9: 39.99 | E9: =D9*$B$3 -> 1919.52 | F9: =C9*$B$3 -> 6719.52 | G9: =F9-E9 -> 4800 | H9: 129.99 | I9: Ilimitado | J9: 100 GB NVMe | K9: Grátis por 1 ano | L9: Diários e sob demanda | M9: Sim | N9: Sim | O9: Sim | P9: Sim
A11: Conferência: o total do contrato calculado bate com o valor do print (ex.: Single 48 x R$ 5,99 = R$ 287,52). Depois dos 48 meses, o valor passa a ser o de renovação.

Sheet Umbler
A1: Umbler - Plano Elástico (valores estimados por mês)
A2: Fonte: print da página da Umbler (docs/hospedagem/umbler.png), consultado em 14/10/2026.
A4: Plano | B4: Preço/mês | C4: Custo 12 meses | D4: RAM | E4: Disco SSD | F4: CPU | G4: Banco de dados | H4: Destaque
A5: Elástico 29 | B5: 29 | C5: =B5*12 -> 348 | D5: 512 MB | E5: 1 GB | F5: 2 Cores | G5: 1 GB
A6: Elástico 39 | B6: 39 | C6: =B6*12 -> 468 | D6: 1 GB | E6: 10 GB | F6: 2 Cores | G6: 1 GB | H6: Mais vendido
A7: Elástico 60 | B7: 60 | C7: =B7*12 -> 720 | D7: 2 GB | E7: 20 GB | F7: 3 Cores | G7: 1 GB
A8: Elástico 195 | B8: 195 | C8: =B8*12 -> 2340 | D8: 6 GB | E8: 40 GB | F8: 4 Cores | G8: 1 GB
A9: Elástico 275 | B9: 275 | C9: =B9*12 -> 3300 | D9: 8 GB | E9: 40 GB | F9: 6 Cores | G9: 1 GB
A11: Os nomes dos planos foram criados pelo grupo a partir do preço, porque o print não mostra nome. O print não informa domínio grátis.
